cg_r_pathway/__init__.py
cg_r_pathway/__main__.py
cg_r_pathway/cli.py
cg_r_pathway/core.py
cg_r_pathway/init.py
cg_r_pathway/main.py
cg_r_pathway/version.py
cg_r_pathway-0.1.6.dist-info/LICENSE
cg_r_pathway-0.1.6.dist-info/METADATA
cg_r_pathway-0.1.6.dist-info/WHEEL
cg_r_pathway-0.1.6.dist-info/entry_points.txt
cg_r_pathway-0.1.6.dist-info/top_level.txt
cg_r_pathway-0.1.6.dist-info/RECORD
