Metadata-Version: 2.1
Name: cg-r-pathway
Version: 0.1.6
Summary: A comprehensive protein reaction coordinate optimization framework
Home-page: https://github.com/simura-works/cg_r_pathway
Author: Bernard Kwadwo Essuman
Author-email: simura.pathway@gmail.com
Classifier: Programming Language :: Python :: 3
Classifier: License :: Other/Proprietary License
Classifier: Operating System :: OS Independent
Requires-Python: >=3.6
License-File: LICENSE
Requires-Dist: numpy
Requires-Dist: matplotlib
Requires-Dist: torch
Requires-Dist: numba
